schiphol_api-0.0.5.dist-info/licenses/LICENSE
schipholapi/__init__.py
schipholapi/api.py
schiphol_api-0.0.5.dist-info/METADATA
schiphol_api-0.0.5.dist-info/WHEEL
schiphol_api-0.0.5.dist-info/top_level.txt
schiphol_api-0.0.5.dist-info/RECORD
